aireadi_loader/__init__.py
aireadi_loader/dataloader.py
aireadi_loader/datasets.py
aireadi_loader/transforms.py
aireadi_loader-0.1.0.dist-info/licenses/LICENSE
aireadi_loader-0.1.0.dist-info/METADATA
aireadi_loader-0.1.0.dist-info/WHEEL
aireadi_loader-0.1.0.dist-info/top_level.txt
aireadi_loader-0.1.0.dist-info/RECORD
