Metadata-Version: 2.4
Name: aireadi-loader
Version: 0.1.0
Summary: Dataloader for the AIREADI dataset.
Home-page: https://github.com/AI-READI/aireadi_loader
Author: Yuka Kihara et al.
Author-email: yk73@uw.edu
License: BSD-2-Clause
Classifier: Programming Language :: Python :: 3
Classifier: License :: OSI Approved :: BSD License
Requires-Python: >=3.10, <3.12
License-File: LICENSE
Requires-Dist: numpy
Requires-Dist: torch==2.4.1
Requires-Dist: tqdm
Requires-Dist: pydicom>=3.0.0
Requires-Dist: pandas>=2.2.2
Requires-Dist: monai>=1.3.0
Dynamic: author
Dynamic: author-email
Dynamic: classifier
Dynamic: description
Dynamic: description-content-type
Dynamic: home-page
Dynamic: license
Dynamic: license-file
Dynamic: requires-dist
Dynamic: requires-python
Dynamic: summary
